Metadata-Version: 2.1
Name: ibcyclonediff
Version: 0.3.8
Summary: Software Bill of Material (SBOM) difference tool
Home-page: https://github.com/threehook/ibcyclonediff
Author: Ton van de Ven
Author-email: threehook@hotmail.com
Maintainer: Ton van de Ven
Maintainer-email: threehook@hotmail.com
License: Apache_2.0
Keywords: security,tools,SBOM,DevSecOps,SPDX,CycloneDX
Classifier: Development Status :: 3 - Alpha
Classifier: Intended Audience :: Developers
Classifier: License :: OSI Approved :: Apache Software License
Classifier: Natural Language :: English
Classifier: Operating System :: OS Independent
Classifier: Programming Language :: Python :: 3.7
Classifier: Programming Language :: Python :: 3.8
Classifier: Programming Language :: Python :: 3.9
Classifier: Programming Language :: Python :: 3.10
Classifier: Programming Language :: Python :: Implementation :: CPython
Classifier: Programming Language :: Python :: Implementation :: PyPy
Requires-Python: >=3.7
License-File: LICENSE
